CHANGELOG.txt
LICENSE.txt
MANIFEST.in
README.rst
lektor_cssbuild.py
setup.cfg
setup.py
lektor_cssbuild.egg-info/PKG-INFO
lektor_cssbuild.egg-info/SOURCES.txt
lektor_cssbuild.egg-info/dependency_links.txt
lektor_cssbuild.egg-info/entry_points.txt
lektor_cssbuild.egg-info/requires.txt
lektor_cssbuild.egg-info/top_level.txt