Metadata-Version: 1.1
Name: lektor-cssbuild
Version: 0.3
Summary: A Lektor plugin for building CSS files
Home-page: https://github.com/uyar/lektor-cssbuild
Author: H. Turgut Uyar
Author-email: uyar@tekir.org
License: BSD
Keywords: lektor plugin static-site CMS sass uncss cssmin
Platform: UNKNOWN
Classifier: Development Status :: 4 - Beta
Classifier: Environment :: Plugins
Classifier: Environment :: Web Environment
Classifier: Framework :: Lektor
Classifier: License :: OSI Approved :: BSD License
